frexco_pylogger/__init__.py
frexco_pylogger/functions.py
frexco_pylogger-0.2.1.dist-info/METADATA
frexco_pylogger-0.2.1.dist-info/WHEEL
frexco_pylogger-0.2.1.dist-info/top_level.txt
frexco_pylogger-0.2.1.dist-info/RECORD
