Metadata-Version: 2.1
Name: frexco-pylogger
Version: 0.2.1
Summary: Python library for logging with colors and http status code.
Home-page: https://github.com/frexco-digital/frexco-pylogger.git
Keywords: logs logging logger
Classifier: Intended Audience :: Developers
Classifier: Programming Language :: Python
Classifier: Programming Language :: Python :: 3.10
Requires-Dist: requests
